tests/__init__.py
tests/test_base.py
tests/test_mlpclassifier.py
tests/test_mlpregressor.py
tests/test_preprocessing.py
tests/test_regressor.py
tnlearn/TN_base.py
tnlearn/__init__.py
tnlearn/activation_function.py
tnlearn/base.py
tnlearn/base1.py
tnlearn/loss_function.py
tnlearn/mlpclassifier.py
tnlearn/mlpregressor.py
tnlearn/neurons.py
tnlearn/optimizer.py
tnlearn/poly_regressor.py
tnlearn/preprocessing.py
tnlearn/regressor.py
tnlearn/seeds.py
tnlearn/utils.py
tnlearn/visualize.py
tnlearn-0.1.1.dist-info/licenses/LICENSE
tnlearn-0.1.1.dist-info/METADATA
tnlearn-0.1.1.dist-info/WHEEL
tnlearn-0.1.1.dist-info/top_level.txt
tnlearn-0.1.1.dist-info/RECORD
