Metadata-Version: 2.4
Name: tnlearn
Version: 0.1.1
Summary: A Python package that uses task-based neurons to build neural networks.
Home-page: https://github.com/NewT123-WM/tnlearn
Author: Meng WANG
Author-email: wangmeng22@stu.hit.edu.cn
Classifier: Programming Language :: Python :: 3
Classifier: License :: OSI Approved :: BSD License
Classifier: Operating System :: OS Independent
Requires-Python: ~=3.8
License-File: LICENSE
Requires-Dist: torch~=2.1.0
Requires-Dist: numpy~=1.26.0
Requires-Dist: scikit-learn~=1.4.0
Requires-Dist: pandas~=2.2.0
Requires-Dist: sympy~=1.12
Requires-Dist: tqdm~=4.66.0
Requires-Dist: matplotlib~=3.8.0
Requires-Dist: ipython~=8.18.0
Requires-Dist: torchinfo~=1.8.0
Requires-Dist: h5py~=3.10.0
Requires-Dist: setuptools>=40.0.0
Dynamic: author
Dynamic: author-email
Dynamic: classifier
Dynamic: description
Dynamic: description-content-type
Dynamic: home-page
Dynamic: license-file
Dynamic: requires-dist
Dynamic: requires-python
Dynamic: summary
